README.md
dyatel.py
setup.py
dyatel.egg-info/PKG-INFO
dyatel.egg-info/SOURCES.txt
dyatel.egg-info/dependency_links.txt
dyatel.egg-info/requires.txt
dyatel.egg-info/top_level.txt