Metadata-Version: 1.0
Name: dyatel
Version: 0.0.4
Summary: UNKNOWN
Home-page: UNKNOWN
Author: Vyacheslav Anzhiganov
Author-email: vanzhiganov@ya.ru
License: UNKNOWN
Platform: UNKNOWN
